avron_parser/__init__.py
avron_parser/inline_parser.py
avron_parser/parser.py
avron_parser/settings_parser.py
avron_parser-0.2.1.dist-info/LICENSE
avron_parser-0.2.1.dist-info/METADATA
avron_parser-0.2.1.dist-info/WHEEL
avron_parser-0.2.1.dist-info/top_level.txt
avron_parser-0.2.1.dist-info/RECORD
