Metadata-Version: 2.2
Name: avron-parser
Version: 0.2.1
Summary: A parser for AVRON (A Very Readable Object Notation)
Home-page: https://github.com/kohanmathers/avron-parser
Author: Kohan Mathers
Author-email: Kohan Mathers <mathers.kohan@gmail.com>
Project-URL: Homepage, https://github.com/kohanmathers/avron-parser
Classifier: Programming Language :: Python :: 3
Classifier: License :: OSI Approved :: MIT License
Classifier: Operating System :: OS Independent
Requires-Python: >=3.6
License-File: LICENSE
Dynamic: author
Dynamic: home-page
Dynamic: requires-python
